xmltoxsd/__init__.py
xmltoxsd/schema_inferer.py
xmltoxsd/xml_parser.py
xmltoxsd/xsd_generator.py
xmltoxsd-0.1.1.dist-info/LICENSE
xmltoxsd-0.1.1.dist-info/METADATA
xmltoxsd-0.1.1.dist-info/WHEEL
xmltoxsd-0.1.1.dist-info/top_level.txt
xmltoxsd-0.1.1.dist-info/RECORD
