Metadata-Version: 2.1
Name: xmltoxsd
Version: 0.1.1
Summary: A library for converting XML documents to XSD schemas.
Author-email: Mustansir Godhrawala <mustansirgodhrawala9@gmail.com>
License: MIT License
Project-URL: homepage, https://github.com/Mustangodhra/xmltoxsd
Keywords: XML,XSD,schema,conversion
Classifier: Development Status :: 3 - Alpha
Classifier: Intended Audience :: Developers
Classifier: Topic :: Software Development :: Libraries :: Python Modules
Classifier: License :: OSI Approved :: MIT License
Classifier: Programming Language :: Python :: 3
Classifier: Programming Language :: Python :: 3.6
Classifier: Programming Language :: Python :: 3.7
Classifier: Programming Language :: Python :: 3.8
Classifier: Programming Language :: Python :: 3.9
Classifier: Programming Language :: Python :: 3.10
Classifier: Operating System :: OS Independent
Requires-Python: >=3.6
License-File: LICENSE
Requires-Dist: lxml >=4.6.3
